FilecoinBaipishuZhongwenXiaozhengBan/README.md
FilecoinBaipishuZhongwenXiaozhengBan/__init__.py
FilecoinBaipishuZhongwenXiaozhengBan/__main__.py
FilecoinBaipishuZhongwenXiaozhengBan/file.epub
FilecoinBaipishuZhongwenXiaozhengBan/index.html
FilecoinBaipishuZhongwenXiaozhengBan/css/__init__.py
FilecoinBaipishuZhongwenXiaozhengBan/css/annotations.css
FilecoinBaipishuZhongwenXiaozhengBan/css/main.css
FilecoinBaipishuZhongwenXiaozhengBan/css/normalize.css
FilecoinBaipishuZhongwenXiaozhengBan/css/popup.css
FilecoinBaipishuZhongwenXiaozhengBan/font/__init__.py
FilecoinBaipishuZhongwenXiaozhengBan/font/fontello.eot
FilecoinBaipishuZhongwenXiaozhengBan/font/fontello.svg
FilecoinBaipishuZhongwenXiaozhengBan/font/fontello.ttf
FilecoinBaipishuZhongwenXiaozhengBan/font/fontello.woff
FilecoinBaipishuZhongwenXiaozhengBan/img/__init__.py
FilecoinBaipishuZhongwenXiaozhengBan/img/annotator-glyph-sprite.png
FilecoinBaipishuZhongwenXiaozhengBan/img/annotator-icon-sprite.png
FilecoinBaipishuZhongwenXiaozhengBan/img/apple-touch-icon.png
FilecoinBaipishuZhongwenXiaozhengBan/img/cancelfullscreen.png
FilecoinBaipishuZhongwenXiaozhengBan/img/close.png
FilecoinBaipishuZhongwenXiaozhengBan/img/fullscreen.png
FilecoinBaipishuZhongwenXiaozhengBan/img/loader.gif
FilecoinBaipishuZhongwenXiaozhengBan/img/menu-icon.png
FilecoinBaipishuZhongwenXiaozhengBan/img/save.png
FilecoinBaipishuZhongwenXiaozhengBan/img/saved.png
FilecoinBaipishuZhongwenXiaozhengBan/img/settings-s.png
FilecoinBaipishuZhongwenXiaozhengBan/img/settings.png
FilecoinBaipishuZhongwenXiaozhengBan/img/star.png
FilecoinBaipishuZhongwenXiaozhengBan/js/__init__.py
FilecoinBaipishuZhongwenXiaozhengBan/js/epub.js
FilecoinBaipishuZhongwenXiaozhengBan/js/epub.min.js
FilecoinBaipishuZhongwenXiaozhengBan/js/epub.min.map
FilecoinBaipishuZhongwenXiaozhengBan/js/hooks.min.js
FilecoinBaipishuZhongwenXiaozhengBan/js/hooks.min.map
FilecoinBaipishuZhongwenXiaozhengBan/js/reader.js
FilecoinBaipishuZhongwenXiaozhengBan/js/reader.js.map
filecoin_baipishu_zhongwen_xiaozheng_ban-2024.3.4.0.dist-info/METADATA
filecoin_baipishu_zhongwen_xiaozheng_ban-2024.3.4.0.dist-info/WHEEL
filecoin_baipishu_zhongwen_xiaozheng_ban-2024.3.4.0.dist-info/entry_points.txt
filecoin_baipishu_zhongwen_xiaozheng_ban-2024.3.4.0.dist-info/top_level.txt
filecoin_baipishu_zhongwen_xiaozheng_ban-2024.3.4.0.dist-info/RECORD
